sympde/__init__.py
sympde/old_sympy_utilities.py
sympde/version.py
sympde/calculus/__init__.py
sympde/calculus/core.py
sympde/calculus/errors.py
sympde/calculus/matrices.py
sympde/calculus/tests/__init__.py
sympde/calculus/tests/test_calculus.py
sympde/core/__init__.py
sympde/core/algebra.py
sympde/core/basic.py
sympde/core/utils.py
sympde/core/tests/__init__.py
sympde/core/tests/test_utils.py
sympde/expr/__init__.py
sympde/expr/basic.py
sympde/expr/equation.py
sympde/expr/errors.py
sympde/expr/evaluation.py
sympde/expr/expr.py
sympde/expr/tests/__init__.py
sympde/expr/tests/test_equation_2d.py
sympde/expr/tests/test_essential_bc.py
sympde/expr/tests/test_expr.py
sympde/expr/tests/test_find_2d.py
sympde/expr/tests/test_newton_2d.py
sympde/expr/tests/test_tensor_2d.py
sympde/exterior/__init__.py
sympde/exterior/calculus.py
sympde/exterior/compiler.py
sympde/exterior/datatype.py
sympde/exterior/form.py
sympde/exterior/inference.py
sympde/exterior/tests/__init__.py
sympde/exterior/tests/test_compiler.py
sympde/exterior/tests/test_datatype.py
sympde/exterior/tests/test_exterior.py
sympde/exterior/tests/test_inference.py
sympde/printing/__init__.py
sympde/printing/latex.py
sympde/printing/tests/__init__.py
sympde/printing/tests/test_latex.py
sympde/topology/__init__.py
sympde/topology/analytical_mapping.py
sympde/topology/basic.py
sympde/topology/callable_mapping.py
sympde/topology/datatype.py
sympde/topology/derivatives.py
sympde/topology/domain.py
sympde/topology/mapping.py
sympde/topology/measure.py
sympde/topology/space.py
sympde/topology/tests/__init__.py
sympde/topology/tests/test_callable_mapping.py
sympde/topology/tests/test_derivatives.py
sympde/topology/tests/test_field_2d.py
sympde/topology/tests/test_gallery.py
sympde/topology/tests/test_logical_expr.py
sympde/topology/tests/test_mapping.py
sympde/topology/tests/test_space.py
sympde/topology/tests/test_symbolic_expr.py
sympde/topology/tests/test_topology.py
sympde/utilities/__init__.py
sympde-0.19.2.dist-info/licenses/LICENSE
sympde-0.19.2.dist-info/METADATA
sympde-0.19.2.dist-info/WHEEL
sympde-0.19.2.dist-info/top_level.txt
sympde-0.19.2.dist-info/RECORD
