Metadata-Version: 2.4
Name: sympde
Version: 0.19.2
Summary: Symbolic calculus for partial differential equations (and variational forms)
Author-email: Ahmed Ratnani <ratnaniahmed@gmail.com>
Maintainer: Said Hadjout
Maintainer-email: Yaman Güçlü <yaman.guclu@gmail.com>
License: MIT License
Project-URL: Repository, https://github.com/pyccel/sympde
Keywords: math
Classifier: Programming Language :: Python :: 3
Requires-Python: >=3.9
License-File: LICENSE
Requires-Dist: sympy<1.10,>=1.5
Requires-Dist: h5py
Requires-Dist: pytest
Requires-Dist: pyyaml
Requires-Dist: numpy
Requires-Dist: matplotlib
Dynamic: license-file
